aionetschool/__init__.py
aionetschool/client.py
aionetschool/client_wrapper.py
aionetschool/exceptions.py
aionetschool/enums/__init__.py
aionetschool/enums/base.py
aionetschool/enums/role.py
aionetschool/types/__init__.py
aionetschool/types/_base.py
aionetschool/types/announcements.py
aionetschool/types/assignment.py
aionetschool/types/attachment.py
aionetschool/types/diary.py
aionetschool/types/mail.py
aionetschool/types/message.py
aionetschool/types/school.py
aionetschool/types/student.py
aionetschool-1.0.1.dist-info/licenses/LICENSE
aionetschool-1.0.1.dist-info/METADATA
aionetschool-1.0.1.dist-info/WHEEL
aionetschool-1.0.1.dist-info/top_level.txt
aionetschool-1.0.1.dist-info/RECORD
